graphem_rapids/__init__.py
graphem_rapids/benchmark.py
graphem_rapids/datasets.py
graphem_rapids/generators.py
graphem_rapids/influence.py
graphem_rapids/visualization.py
graphem_rapids/backends/__init__.py
graphem_rapids/backends/embedder_cuvs.py
graphem_rapids/backends/embedder_pytorch.py
graphem_rapids/utils/__init__.py
graphem_rapids/utils/backend_selection.py
graphem_rapids/utils/memory_management.py
graphem_rapids-0.2.1.dist-info/licenses/LICENSE
scripts/run_comprehensive_tests.py
graphem_rapids-0.2.1.dist-info/METADATA
graphem_rapids-0.2.1.dist-info/WHEEL
graphem_rapids-0.2.1.dist-info/entry_points.txt
graphem_rapids-0.2.1.dist-info/top_level.txt
graphem_rapids-0.2.1.dist-info/RECORD
