Metadata-Version: 2.4
Name: graphem-rapids
Version: 0.2.1
Summary: A graph embedding library with PyTorch and RAPIDS acceleration
Home-page: https://github.com/sashakolpakov/graphem-rapids
Author: Alexander Kolpakov (UATX), Igor Rivin (Temple University)
Author-email: Alexander Kolpakov <akolpakov@uaustin.org>, Igor Rivin <rivin@temple.edu>
Maintainer-email: Alexander Kolpakov <akolpakov@uaustin.org>
License: MIT
Project-URL: Homepage, https://github.com/sashakolpakov/graphem-rapids
Project-URL: Documentation, https://sashakolpakov.github.io/graphem-rapids/
Project-URL: Repository, https://github.com/sashakolpakov/graphem-rapids
Project-URL: Bug Reports, https://github.com/sashakolpakov/graphem-rapids/issues
Project-URL: Paper, https://arxiv.org/abs/2506.07435
Project-URL: Original GraphEm, https://github.com/sashakolpakov/graphem
Keywords: graph embedding,node influence,centrality measures,network analysis,force layout,PyTorch,CUDA,RAPIDS
Classifier: Development Status :: 3 - Alpha
Classifier: Intended Audience :: Science/Research
Classifier: Topic :: Scientific/Engineering :: Mathematics
Classifier: Topic :: Scientific/Engineering :: Information Analysis
Classifier: Programming Language :: Python :: 3
Classifier: Programming Language :: Python :: 3.8
Classifier: Programming Language :: Python :: 3.9
Classifier: Programming Language :: Python :: 3.10
Classifier: Programming Language :: Python :: 3.11
Classifier: License :: OSI Approved :: MIT License
Classifier: Operating System :: OS Independent
Requires-Python: >=3.8
License-File: LICENSE
Requires-Dist: torch>=2.0.0
Requires-Dist: numpy>=1.21.0
Requires-Dist: matplotlib>=3.5.0
Requires-Dist: networkx>=2.6.0
Requires-Dist: pandas>=1.3.0
Requires-Dist: plotly>=5.5.0
Requires-Dist: scipy>=1.7.0
Requires-Dist: ndlib>=5.1.0
Requires-Dist: loguru>=0.6.0
Requires-Dist: requests>=2.25.0
Requires-Dist: line_profiler>=4.0.0
Requires-Dist: snakeviz>=2.2.0
Requires-Dist: tensorboard>=2.10.0
Requires-Dist: tqdm>=4.66.0
Requires-Dist: pyinstrument>=5.0.0
Requires-Dist: tabulate>=0.9.0
Provides-Extra: cuda
Requires-Dist: cupy-cuda12x>=10.0.0; extra == "cuda"
Requires-Dist: pykeops>=2.1.0; extra == "cuda"
Provides-Extra: rapids
Requires-Dist: cudf-cu12; extra == "rapids"
Requires-Dist: cuml-cu12; extra == "rapids"
Requires-Dist: cuvs-cu12; extra == "rapids"
Requires-Dist: cupy-cuda12x>=10.0.0; extra == "rapids"
Requires-Dist: pykeops>=2.1.0; extra == "rapids"
Provides-Extra: docs
Requires-Dist: sphinx>=4.0.0; extra == "docs"
Requires-Dist: sphinx_rtd_theme>=1.0.0; extra == "docs"
Requires-Dist: sphinx-autodoc-typehints>=1.12.0; extra == "docs"
Requires-Dist: myst-parser>=0.17.0; extra == "docs"
Provides-Extra: test
Requires-Dist: pytest>=6.0.0; extra == "test"
Requires-Dist: pytest-cov>=2.12.0; extra == "test"
Requires-Dist: pytest-xdist>=2.3.0; extra == "test"
Provides-Extra: dev
Requires-Dist: pytest>=6.0.0; extra == "dev"
Requires-Dist: pytest-cov>=2.12.0; extra == "dev"
Requires-Dist: pytest-xdist>=2.3.0; extra == "dev"
Requires-Dist: sphinx>=4.0.0; extra == "dev"
Requires-Dist: sphinx_rtd_theme>=1.0.0; extra == "dev"
Requires-Dist: sphinx-autodoc-typehints>=1.12.0; extra == "dev"
Requires-Dist: myst-parser>=0.17.0; extra == "dev"
Requires-Dist: black>=22.0.0; extra == "dev"
Requires-Dist: isort>=5.10.0; extra == "dev"
Requires-Dist: flake8>=4.0.0; extra == "dev"
Requires-Dist: mypy>=0.950; extra == "dev"
Provides-Extra: all
Requires-Dist: cudf-cu12; extra == "all"
Requires-Dist: cuml-cu12; extra == "all"
Requires-Dist: cuvs-cu12; extra == "all"
Requires-Dist: cupy-cuda12x>=10.0.0; extra == "all"
Requires-Dist: pykeops>=2.1.0; extra == "all"
Requires-Dist: sphinx>=4.0.0; extra == "all"
Requires-Dist: sphinx_rtd_theme>=1.0.0; extra == "all"
Requires-Dist: sphinx-autodoc-typehints>=1.12.0; extra == "all"
Requires-Dist: myst-parser>=0.17.0; extra == "all"
Requires-Dist: pytest>=6.0.0; extra == "all"
Requires-Dist: pytest-cov>=2.12.0; extra == "all"
Requires-Dist: pytest-xdist>=2.3.0; extra == "all"
Dynamic: author
Dynamic: home-page
Dynamic: license-file
Dynamic: requires-python
